wagtailapproval/__init__.py
wagtailapproval/_signals.py
wagtailapproval/approvalitem.py
wagtailapproval/apps.py
wagtailapproval/forms.py
wagtailapproval/menu.py
wagtailapproval/models.py
wagtailapproval/signals.py
wagtailapproval/urls.py
wagtailapproval/views.py
wagtailapproval/wagtail_hooks.py
wagtailapproval/migrations/0001_initial.py
wagtailapproval/migrations/__init__.py
wagtailapproval/templates/wagtailapproval/approve.html
wagtailapproval/templates/wagtailapproval/cancel.html
wagtailapproval/templates/wagtailapproval/index.html
wagtailapproval/templates/wagtailapproval/reject.html
wagtailapproval/templates/wagtailapproval/ticket_list.html
wagtailapproval/templates/wagtailapproval/admin/index.html
wagtailapproval/templates/wagtailapproval/admin/pipeline.html
wagtailapproval/templates/wagtailapproval/admin/pipeline_list.html
wagtailapproval/templates/wagtailapproval/admin/step.html
wagtailapproval/templates/wagtailapproval/admin/step_list.html
wagtailapproval/templates/wagtailapproval/admin/ticket_list.html
wagtailapproval/templatetags/__init__.py
wagtailapproval/templatetags/wagtailapproval_admin.py
wagtailapproval-0.5.4.dist-info/DESCRIPTION.rst
wagtailapproval-0.5.4.dist-info/METADATA
wagtailapproval-0.5.4.dist-info/RECORD
wagtailapproval-0.5.4.dist-info/WHEEL
wagtailapproval-0.5.4.dist-info/metadata.json
wagtailapproval-0.5.4.dist-info/top_level.txt
