Metadata-Version: 2.0
Name: wagtailapproval
Version: 0.5.4
Summary: Wagtail Approval pipeline
Home-page: https://github.com/absperf/wagtailapproval
Author: Taylor C. Richberger <tcr@absolute-performance.com>
Author-email: tcr@absolute-performance.com
License: BSD 2-Clause
Platform: UNKNOWN
Classifier: Development Status :: 4 - Beta
Classifier: Environment :: Web Environment
Classifier: Framework :: Django
Classifier: Intended Audience :: Developers
Classifier: License :: OSI Approved :: BSD License
Classifier: Operating System :: OS Independent
Classifier: Programming Language :: Python
Classifier: Programming Language :: Python :: 3
Classifier: Programming Language :: Python :: 3.5
Classifier: Programming Language :: Python :: Implementation :: CPython
Classifier: Topic :: Software Development :: Libraries
Classifier: Topic :: Software Development :: Libraries :: Python Modules
Requires-Dist: django (>=1.8)
Requires-Dist: wagtail (>=1.11)
Requires-Dist: enum34; python_version < "3.4"
